{
  "entities": {
    "FenceData": {
      "$schema": "http://json-schema.org/draft-07/schema#",
      "title": "FenceData",
      "type": "object",
      "description": "Represents the real-time state of the electric fence in Firebase Realtime Database.",
      "properties": {
        "status": {
          "type": "string",
          "description": "The current status of the fence (e.g., 'LEGAL', 'ILLEGAL_NO_PULSE')."
        },
        "source": {
          "type": "string",
          "description": "Indicates if the status was set by the 'web' admin panel."
        }
      },
      "required": [
        "status",
        "source"
      ]
    },
    "Sensors": {
      "$schema": "http://json-schema.org/draft-07/schema#",
      "title": "Sensors",
      "type": "object",
      "description": "Represents sensor data from the IoT device in Realtime Database.",
      "properties": {
        "gas": {
          "type": "number",
          "description": "The gas level reading from the MQ sensor."
        }
      },
      "required": [
        "gas"
      ]
    },
    "SensorData": {
      "$schema": "http://json-schema.org/draft-07/schema#",
      "title": "SensorData",
      "type": "object",
      "description": "Represents sensor data from the IoT device. This is for the original dashboard and is separate from the new Realtime Database structure.",
      "properties": {
        "id": {
          "type": "string",
          "description": "Unique identifier for the SensorData entity."
        },
        "gasValue": {
          "type": "number",
          "description": "The gas level reading from the MQ sensor (e.g., in PPM)."
        },
        "lastRead": {
          "type": "string",
          "description": "Timestamp of when sensor data was last read.",
          "format": "date-time"
        }
      },
      "required": [
        "id",
        "gasValue",
        "lastRead"
      ]
    }
  },
  "auth": {
    "providers": [
      "password",
      "anonymous"
    ]
  },
  "firestore": {
    "structure": [
      {
        "path": "/fence",
        "definition": {
          "entityName": "FenceData",
          "schema": {
            "$ref": "#/backend/entities/FenceData"
          },
          "description": "Stores the fence state (status and source) in Realtime Database."
        }
      },
      {
        "path": "/sensors",
        "definition": {
          "entityName": "Sensors",
          "schema": {
            "$ref": "#/backend/entities/Sensors"
          },
          "description": "Stores sensor data (e.g., gas) from the ESP8266 in Realtime Database."
        }
      },
      {
        "path": "/sensor_data/{sensorDataId}",
        "definition": {
          "entityName": "SensorData",
          "schema": {
            "$ref": "#/backend/entities/SensorData"
          },
          "description": "Stores sensor data for the original dashboard. This path is in Firestore.",
          "params": [
            {
              "name": "sensorDataId",
              "description": "Unique identifier for the sensor data document."
            }
          ]
        }
      }
    ],
    "reasoning": "The application uses Firebase Realtime Database for two-way data synchronization between the web app and an ESP8266 device. Data is split into two main nodes: `/fence` for device status and control source, and `/sensors` for data from the device's sensors (like gas). This flat structure is simple for a microcontroller to consume. The original Firestore structure for `sensor_data` is kept for the unmodified `/dashboard` page."
  }
}
